mlpype/sklearn/__init__.py
mlpype/sklearn/data/__init__.py
mlpype/sklearn/data/data_frame_source.py
mlpype/sklearn/data/sklearn_data.py
mlpype/sklearn/data/sql_source.py
mlpype/sklearn/model/__init__.py
mlpype/sklearn/model/sklearn_base_type.py
mlpype/sklearn/model/sklearn_model.py
mlpype/sklearn/pipeline/__init__.py
mlpype/sklearn/pipeline/numpy_type_checker.py
mlpype/sklearn/pipeline/pandas_type_checker.py
mlpype_sklearn-0.6.12.dist-info/METADATA
mlpype_sklearn-0.6.12.dist-info/WHEEL
mlpype_sklearn-0.6.12.dist-info/RECORD
